{
  "Anatolia": {
    "id": "http://www.wikidata.org/entity/Q51614"
  },
  "Balkans": {
    "id": "http://www.wikidata.org/entity/Q23522"
  },
  "British Isles": {
    "id": "http://www.wikidata.org/entity/Q38272"
  },
  "Caucasus": {
    "id": "http://www.wikidata.org/entity/Q18869"
  },
  "Corsica": {
    "id": "http://www.wikidata.org/entity/Q14112"
  },
  "Crete": {
    "id": "http://www.wikidata.org/entity/Q34374"
  },
  "East Africa": {
    "id": "http://www.wikidata.org/entity/Q27407"
  },
  "Eastern Europe": {
    "id": "http://www.wikidata.org/entity/Q27468"
  },
  "Fertile Crescent": {
    "id": "http://www.wikidata.org/entity/Q170526"
  },
  "Indochina": {
    "id": "http://www.wikidata.org/entity/Q43467"
  },
  "Ireland": {
    "id": "http://www.wikidata.org/entity/Q22890"
  },
  "Judea": {
    "id": "http://www.wikidata.org/entity/Q104028"
  },
  "Korean Peninsula": {
    "id": "http://www.wikidata.org/entity/Q483134"
  },
  "Latium": {
    "id": "http://www.wikidata.org/entity/Q1048669"
  },
  "Levant": {
    "id": "http://www.wikidata.org/entity/Q81483"
  },
  "Levant": {
    "id": "http://www.wikidata.org/entity/Q81483"
  },
  "Majorca": {
    "id": "http://www.wikidata.org/entity/Q8828"
  },
  "Malay Peninsula": {
    "id": "http://www.wikidata.org/entity/Q18758"
  },
  "Mediterranean Basin": {
    "id": "http://www.wikidata.org/entity/Q72499"
  },
  "Mesoamerica": {
    "id": "http://www.wikidata.org/entity/Q13703"
  },
  "Messenia": {
    "id": "http://www.wikidata.org/entity/Q1247159"
  },
  "Middle East": {
    "id": "http://www.wikidata.org/entity/Q7204"
  },
  "New England": {
    "id": "http://www.wikidata.org/entity/Q18389"
  },
  "North Africa": {
    "id": "http://www.wikidata.org/entity/Q27381"
  },
  "North India": {
    "id": "http://www.wikidata.org/entity/Q1058785"
  },
  "Northern Europe": {
    "id": "http://www.wikidata.org/entity/Q27479"
  },
  "Rhineland": {
    "id": "http://www.wikidata.org/entity/Q152243"
  },
  "South Caucasus": {
    "id": "http://www.wikidata.org/entity/Q200173"
  },
  "South India": {
    "id": "http://www.wikidata.org/entity/Q542146"
  },
  "Southern Africa": {
    "id": "http://www.wikidata.org/entity/Q27394"
  },
  "Southern Europe": {
    "id": "http://www.wikidata.org/entity/Q27449"
  },
  "Tibet": {
    "id": "http://www.wikidata.org/entity/Q17252"
  },
  "West Africa": {
    "id": "http://www.wikidata.org/entity/Q4412"
  },
  "West India": {
    "id": "http://www.wikidata.org/entity/Q1151567"
  },
  "Western Europe": {
    "id": "http://www.wikidata.org/entity/Q27496"
  }
}
